[
  {
    "id": 1759409046419,
    "nick": "123123",
    "vk": "123123",
    "password": "123123",
    "status": "approved",
    "createdAt": "2025-10-02T12:44:06.419Z"
  },
  {
    "id": 1759409211378,
    "nick": "1231231",
    "vk": "123123",
    "password": "123123",
    "status": "approved",
    "createdAt": "2025-10-02T12:46:51.378Z"
  },
  {
    "id": 1759409511897,
    "nick": "12312311",
    "vk": "123123",
    "password": "123123",
    "status": "approved",
    "createdAt": "2025-10-02T12:51:51.897Z"
  },
  {
    "id": 1759412972668,
    "nick": "11",
    "vk": "11",
    "password": "123123",
    "status": "approved",
    "createdAt": "2025-10-02T13:49:32.668Z"
  }
]